{"title":"Teddybears - Devils Music 2010 MP3 TheCaptain","uid":6051498,"size":94755449,"categoryP":"audio","categoryS":"music","magnet":"?xt=urn:btih:02876b5d05a4e6274d53f55f7f2f074dfea9459d&amp;dn=Teddybears+-+Devils+Music+2010+MP3+TheCaptain&amp;tr=udp%3A%2F%2Ftracker.openbittorrent.com%3A80&amp;tr=udp%3A%2F%2Fopen.demonii.com%3A1337&amp;tr=udp%3A%2F%2Ftracker.coppersurfer.tk%3A6969&amp;tr=udp%3A%2F%2Fexodus.desync.com%3A6969","seeders":4,"leechers":0,"uploader":"thecaptainofsweden","files":-1,"time":1292752652,"description":"================================================================================\n\n Teddybears:\n Devils Music (2010)\n\n- MP3 - 320kbit/s - CBR -\n\nTracklist:\n\n1.  Rocket Scientist (feat. Eve)                       3:07\n\n2.  Get Mama a House (feat. Desmond Forster)           3:22\n\n3.  Cardiac Arrest (feat. Maipei)                      3:00\n\n4.  Glow in the Dark                                   3:33\n\n5.  Get Fresh with You (feat. Redfox)                  3:14\n\n6.  Cho Cha (feat. Cee-Lo Green &amp; The B-52s)           3:21\n\n7.  Chrystal Meth Christian (feat. The Flaming Lips)   3:44\n\n8.  Cisum Slived                                       4:19\n\n9.  Devil's Music (feat. ADL)                          3:26\n\n10. Tek It Down (feat. Rigo)                           3:05\n\n11. Wolfman                                            4:17\n\n12. Bukowski                                           0:22\n\n\nRipped By TheCaptainOfSweden.\n\nenjoy &amp; seed.\n\n/Captain.\n\n================================================================================","torrent":{"xt":"urn:btih:02876b5d05a4e6274d53f55f7f2f074dfea9459d","amp;dn":"Teddybears+-+Devils+Music+2010+MP3+TheCaptain","amp;tr":["udp%3A%2F%2Ftracker.openbittorrent.com%3A80","udp%3A%2F%2Fopen.demonii.com%3A1337","udp%3A%2F%2Ftracker.coppersurfer.tk%3A6969","udp%3A%2F%2Fexodus.desync.com%3A6969"],"infoHash":"02876b5d05a4e6274d53f55f7f2f074dfea9459d","infoHashBuffer":{"type":"Buffer","data":[2,135,107,93,5,164,230,39,77,83,245,95,127,47,7,77,254,169,69,157]},"announce":[],"urlList":[]}}