{"title":"Ambikapathy (2013) Tamil DVDRip 720p x264 5.1 Manudil ","uid":8766016,"size":1353207511,"categoryP":"video","categoryS":"hd___movies","magnet":"?xt=urn:btih:097326fb8557f1e79e2d891dfaa78569d58d42a1&amp;dn=Ambikapathy+%282013%29+Tamil+DVDRip+720p+x264+5.1+Manudil+&amp;tr=udp%3A%2F%2Ftracker.openbittorrent.com%3A80&amp;tr=udp%3A%2F%2Fopen.demonii.com%3A1337&amp;tr=udp%3A%2F%2Ftracker.coppersurfer.tk%3A6969&amp;tr=udp%3A%2F%2Fexodus.desync.com%3A6969","seeders":4,"leechers":0,"uploader":"manudil","files":5,"time":1375335023,"description":":General:\nComplete name: Ambikapathy (2013) Tamil DVDRip 720p x264 5.1 Manudil\nFormat: Matroska\nFile size: 1.25 GiB\nDuration: 2h 8mn\nOverall Bitrate: 1 400 Kbps\nLanguage: Tamil\nSub Title: English\nRipper: Manudil\nSource: DVD5 @TamilRockrs\n\n\n:Imdb Info:\nIMDB Link: http://www.imdb.com/title/tt2359810/\nIMDB Rating:7.9/10\nRelease Date:21 June 2013 (India)\nGenre: Drama | Romance\n\n\n:Video:\nFormat/Info: Advanced Video Codec\nBitrate: 1 208 Kbps\nWidth: 1 280 pixels\nHeight: 544 pixels\nDisplay aspect ratio: 2.35:1\nFrame rate: 29.970 fps\n\n\n:Audio:\nFormat: Advanced Audio Codec\nNominal Bitrate: 192 kbps\nChannel(s): 6 channels,Front: L C R, Side: L R, LFE\nSampling rate: 48.0 KHz\n\n\n:Cast:\nDhanush, Sonam Kapoor, Abhay Deol | See full cast and crew\n\n\n:Plot:\nThe pundit's son Kundan (Dhanush) has fallen for the girl at first sight. That they're both kids makes us dismiss it as a meaningless crush. But a few years later, the boy is still in love ... \n &lt;a href=&quot;\nhttp://thumbnails101.imagebam.com/26811/c4c2a9268103111.jpg&quot; rel=&quot;nofollow&quot; target=&quot;_NEW&quot;&gt;\nhttp://thumbnails101.imagebam.com/26811/c4c2a9268103111.jpg&lt;/a&gt; &lt;a href=&quot;\nhttp://thumbnails107.imagebam.com/26811/e8f0c1268103136.jpg&quot; rel=&quot;nofollow&quot; target=&quot;_NEW&quot;&gt;\nhttp://thumbnails107.imagebam.com/26811/e8f0c1268103136.jpg&lt;/a&gt; &lt;a href=&quot;\nhttp://thumbnails101.imagebam.com/26811/18d163268103152.jpg&quot; rel=&quot;nofollow&quot; target=&quot;_NEW&quot;&gt;\nhttp://thumbnails101.imagebam.com/26811/18d163268103152.jpg&lt;/a&gt; &lt;a href=&quot;\nhttp://thumbnails107.imagebam.com/26811/ac37f3268103161.jpg&quot; rel=&quot;nofollow&quot; target=&quot;_NEW&quot;&gt;\nhttp://thumbnails107.imagebam.com/26811/ac37f3268103161.jpg&lt;/a&gt; &lt;a href=&quot;\nhttp://thumbnails105.imagebam.com/26811/3f0f97268103176.jpg&quot; rel=&quot;nofollow&quot; target=&quot;_NEW&quot;&gt;\nhttp://thumbnails105.imagebam.com/26811/3f0f97268103176.jpg&lt;/a&gt; &lt;a href=&quot;\nhttp://thumbnails106.imagebam.com/26811/f84c1f268103192.jpg&quot; rel=&quot;nofollow&quot; target=&quot;_NEW&quot;&gt;\nhttp://thumbnails106.imagebam.com/26811/f84c1f268103192.jpg&lt;/a&gt; &lt;a href=&quot;\nhttp://thumbnails106.imagebam.com/26811/ed3c34268103203.jpg&quot; rel=&quot;nofollow&quot; target=&quot;_NEW&quot;&gt;\nhttp://thumbnails106.imagebam.com/26811/ed3c34268103203.jpg&lt;/a&gt;\n\nwe are on FaceBook, Post Your Request, suggestion, and find upcomming Release of Silver RG, you will find all Silver RG Encoders at FB Page so keep in touch\n\n\n\n:Greetz:\nTo All Silver RG Encoders, All SilverTorrentHD Encoders &amp; All Other P2P RGs\n\n:Note:\nMake sure its real Silver RG Release From Silver RG Member,A video sample is included in the folder for those who want to check quality and compatibility before downloading the whole movie.\n\nWe Are Looking For Early Access To Anything You Can Provide CAMS, TS, DVD Screeners, VHS Screeners, DVDRips, Direct Audio, Early Music Release, Anything You Can Provide Seedboxes, Accounts, Dedicated Servers - Contact Us @\n\n:Support:\nTook 5 Hours to Encode &amp; 24 Hours to Upload &amp; Seed\nTook 30 Minutes to Create Description/Screen Shots etc...\nTakes 10 Seconds to say &quot;Thank You&quot;, or 4 seconds to say &quot;Whoooo&quot;","torrent":{"xt":"urn:btih:097326fb8557f1e79e2d891dfaa78569d58d42a1","amp;dn":"Ambikapathy+%282013%29+Tamil+DVDRip+720p+x264+5.1+Manudil+","amp;tr":["udp%3A%2F%2Ftracker.openbittorrent.com%3A80","udp%3A%2F%2Fopen.demonii.com%3A1337","udp%3A%2F%2Ftracker.coppersurfer.tk%3A6969","udp%3A%2F%2Fexodus.desync.com%3A6969"],"infoHash":"097326fb8557f1e79e2d891dfaa78569d58d42a1","infoHashBuffer":{"type":"Buffer","data":[9,115,38,251,133,87,241,231,158,45,137,29,250,167,133,105,213,141,66,161]},"announce":[],"urlList":[]}}