{"title":"Den Som Draeber (2010) a.k.a. Those Who Kill 2 (MULTI SUBS) TBS","uid":6345336,"size":4422674212,"categoryP":"video","categoryS":"movies_dvdr","magnet":"?xt=urn:btih:0bacd86b7d133a4d9f84d18b9cc07559ac541325&amp;dn=Den+Som+Draeber+%282010%29+a.k.a.+Those+Who+Kill+2+%28MULTI+SUBS%29+TBS&amp;tr=udp%3A%2F%2Ftracker.openbittorrent.com%3A80&amp;tr=udp%3A%2F%2Fopen.demonii.com%3A1337&amp;tr=udp%3A%2F%2Ftracker.coppersurfer.tk%3A6969&amp;tr=udp%3A%2F%2Fexodus.desync.com%3A6969","seeders":4,"leechers":2,"uploader":"Vlinder2","files":-1,"time":1303817399,"description":"Den Som Draeber (2010) a.k.a. Those Who Kill (deel 2 - Utopia)\n\nEnglish\n\nAbout the hunt for a type of violent criminal who has yet to strike in Denmark, and who is surrounded by fear and mystique - the serial killer.  \n\n.\n&gt;&gt;&gt;&gt;&gt; @friemke - producties presenteert met trots &lt;&lt;&lt;&lt;&lt;\n&gt;&gt;&gt;&gt;&gt; Voor de liefhebbers van Nordic thrillers: &lt;&lt;&lt;&lt;&lt;\n&gt;&gt;&gt;&gt;&gt; Den Som Draeber (2010) a.k.a. Those Who Kill (deel 2 - Utopia) &lt;&lt;&lt;&lt;&lt;\n\n\n\ncustom ondertiteld in het Nederlands by @friemke\n\n\n\nFilminformatie \nGenre : thriller\nSpeelduur : 82 minuten\nProductiejaar : 2010/2011\n\nDeel 3 en 4 van de succesvolle 10-delige misdaadserie; nu samen als ÃƒÂ©ÃƒÂ©n film.\n\nEen familie wordt vermoord aangetroffen in hun huis.\nEr is niets gestolen en de brute moorden zijn zonder aanwijsbare reden gepleegd.\nThomas is verontrust over deze mysterieuze, brutale, aanval en neemt de zaak op zich.\nTerwijl het onderzoek vordert, wordt er nog een gezin ontvoerd en gevangen gehouden in hun huis.\nDe moordenaar zondert de man af van zijn vrouw en kind om de rol te spelen in zijn \\&quot;eigen\\&quot; familie.\nKatrine en Thomas binnen aan een race tegen de klok om het opsporen van de moordenaar en nog vrije gezin vÃƒÂ³ÃƒÂ³r de moordenaar kans ziet ze te scheiden.\n\n\n\n\nBijzonderheden:\nBron : .mkv van blu-ray\nTV systeem : PAL\nBeeld : 16:9\nTaal : Deens DD5.1\nOndertitels : Deens/ Engels / Fins / Noors / Zweeds / Nederlands, custom by @friemke\nMenu : geen\nExtra\\'s : geen\nCover : een aangepast NL exemplaar @friemke is bijgevoegd, evenals het originele label.\n\n \n  Category : Video \n  Format : DVD5 \n  Source : Retail \n  Subtitle : English subs English subs (optional) optional  \n  Genre : Thriller  \n  Status : Done Uploading \n  Weblink : http://www.gucca.dk/blu-ray-film/den-som-draeber-vol.-1-blu-ray_128938.html \n &lt;a href=&quot;\nhttp://www.imdb.com/title/tt1565810/&quot; rel=&quot;nofollow&quot; target=&quot;_NEW&quot;&gt;\nhttp://www.imdb.com/title/tt1565810/&lt;/a&gt;\n\nTBS\n ","torrent":{"xt":"urn:btih:0bacd86b7d133a4d9f84d18b9cc07559ac541325","amp;dn":"Den+Som+Draeber+%282010%29+a.k.a.+Those+Who+Kill+2+%28MULTI+SUBS%29+TBS","amp;tr":["udp%3A%2F%2Ftracker.openbittorrent.com%3A80","udp%3A%2F%2Fopen.demonii.com%3A1337","udp%3A%2F%2Ftracker.coppersurfer.tk%3A6969","udp%3A%2F%2Fexodus.desync.com%3A6969"],"infoHash":"0bacd86b7d133a4d9f84d18b9cc07559ac541325","infoHashBuffer":{"type":"Buffer","data":[11,172,216,107,125,19,58,77,159,132,209,139,156,192,117,89,172,84,19,37]},"announce":[],"urlList":[]}}