{"title":"Horny Busty Teen Nasty Fuck Pics","uid":11829352,"size":240421725,"categoryP":"porn","categoryS":"pictures","magnet":"?xt=urn:btih:0eff45d592f3e42e89c550b17ae8fa0a15c4e66f&amp;dn=Horny+Busty+Teen+Nasty+Fuck+Pics&amp;tr=udp%3A%2F%2Ftracker.openbittorrent.com%3A80&amp;tr=udp%3A%2F%2Fopen.demonii.com%3A1337&amp;tr=udp%3A%2F%2Ftracker.coppersurfer.tk%3A6969&amp;tr=udp%3A%2F%2Fexodus.desync.com%3A6969","seeders":4,"leechers":1,"uploader":"HighCode","files":77,"time":1429583444,"description":"Horny Busty Teen Nasty Fuck Pics\n\nHorny Busty Teen Nasty Fuck Pics\nSize: 229MB | Pictures: 76 | Resolution: 2000Ã—3000 \n\n  Screenshots:  &lt;a href=&quot;\nhttp://imgclover.com/image/mX&quot; rel=&quot;nofollow&quot; target=&quot;_NEW&quot;&gt;\nhttp://imgclover.com/image/mX&lt;/a&gt; &lt;a href=&quot;\nhttp://imgclover.com/image/mU&quot; rel=&quot;nofollow&quot; target=&quot;_NEW&quot;&gt;\nhttp://imgclover.com/image/mU&lt;/a&gt; &lt;a href=&quot;\nhttp://imgclover.com/image/mh&quot; rel=&quot;nofollow&quot; target=&quot;_NEW&quot;&gt;\nhttp://imgclover.com/image/mh&lt;/a&gt; &lt;a href=&quot;\nhttp://imgclover.com/image/mr&quot; rel=&quot;nofollow&quot; target=&quot;_NEW&quot;&gt;\nhttp://imgclover.com/image/mr&lt;/a&gt;","torrent":{"xt":"urn:btih:0eff45d592f3e42e89c550b17ae8fa0a15c4e66f","amp;dn":"Horny+Busty+Teen+Nasty+Fuck+Pics","amp;tr":["udp%3A%2F%2Ftracker.openbittorrent.com%3A80","udp%3A%2F%2Fopen.demonii.com%3A1337","udp%3A%2F%2Ftracker.coppersurfer.tk%3A6969","udp%3A%2F%2Fexodus.desync.com%3A6969"],"infoHash":"0eff45d592f3e42e89c550b17ae8fa0a15c4e66f","infoHashBuffer":{"type":"Buffer","data":[14,255,69,213,146,243,228,46,137,197,80,177,122,232,250,10,21,196,230,111]},"announce":[],"urlList":[]}}