{"title":"Predator 2[1990]DvDrip[Eng] HarrHarrr","uid":4766598,"size":733776267,"categoryP":"video","categoryS":"movies","magnet":"?xt=urn:btih:13ea15e21765f9ba4263cf226f56c67788d0f337&amp;dn=Predator+2%5B1990%5DDvDrip%5BEng%5D+HarrHarrr&amp;tr=udp%3A%2F%2Ftracker.openbittorrent.com%3A80&amp;tr=udp%3A%2F%2Fopen.demonii.com%3A1337&amp;tr=udp%3A%2F%2Ftracker.coppersurfer.tk%3A6969&amp;tr=udp%3A%2F%2Fexodus.desync.com%3A6969","seeders":4,"leechers":0,"uploader":"Harrharrr","files":-1,"time":1236891824,"description":"Info.\n\nTitle.......[ Predator 2\nYear........[ 1990 \nGenre.......[ Action | Adventure | Crime | Horror | Sci-Fi | Thriller  \nRuntime.....[ 1h 43m 33s\n\n\nAudio.......[ VBR Mp3 102 Kbps 44100Hz 2ch\nLanguage....[ English\nResolution..[ 608 x 336\nVideo.......[ 830 kbps XviD 25.000 FPS\nQ. Frame....[ 0.163\nDar.........[ 1.810 (38:21)\nSubs........[ English \nFiles.......[ 3 (Third file is the log from AutoGK, movie rendering program)\nSize........[ 699 Mb\nSource......[ DVD\n\nMovie Notes.\n\nPredator 2\n\nCountry: USA\nIMDb Rating: 5.9/10\nDirector: Stephen Hopkins\nCast: Danny Glover, Kevin Peter Hall, Gary Busey, RubÃƒÂ©n Blades, Maria Conchita Alonso, Bill Paxton, Robert Davi, Adam Baldwin, Kent McCord \n       &lt;a href=&quot;\nhttp://www.imdb.com/title/tt0100403/&quot; rel=&quot;nofollow&quot; target=&quot;_NEW&quot;&gt;\nhttp://www.imdb.com/title/tt0100403/&lt;/a&gt;\n\nPlot: Harrigan, a brash policeman who is fighting drug lords in a decaying L.A. finds that the criminals are being killed in a very odd fashion. The federal authorities keep telling him to stay out, even though his own men are also being killed. He catches sight of a nearly invisible alien hunter who is searching for trophies. Harrigan injures the creature and pursues it, becoming the hunter. \n\nEnjoy this movie, and please keep seeding when ur done downloading =)","torrent":{"xt":"urn:btih:13ea15e21765f9ba4263cf226f56c67788d0f337","amp;dn":"Predator+2%5B1990%5DDvDrip%5BEng%5D+HarrHarrr","amp;tr":["udp%3A%2F%2Ftracker.openbittorrent.com%3A80","udp%3A%2F%2Fopen.demonii.com%3A1337","udp%3A%2F%2Ftracker.coppersurfer.tk%3A6969","udp%3A%2F%2Fexodus.desync.com%3A6969"],"infoHash":"13ea15e21765f9ba4263cf226f56c67788d0f337","infoHashBuffer":{"type":"Buffer","data":[19,234,21,226,23,101,249,186,66,99,207,34,111,86,198,119,136,208,243,55]},"announce":[],"urlList":[]}}