{"title":"Survivor.S32E11.720p.WEB-DL.x264-FUM[ettv]","uid":14463892,"size":1467065418,"categoryP":"video","categoryS":"hd___tv_shows","magnet":"?xt=urn:btih:1f67c90dc4b6d58402cdc7fa5cb38f93e73cb08b&amp;dn=Survivor.S32E11.720p.WEB-DL.x264-FUM%5Bettv%5D&amp;tr=udp%3A%2F%2Ftracker.leechers-paradise.org%3A6969&amp;tr=udp%3A%2F%2Fzer0day.ch%3A1337&amp;tr=udp%3A%2F%2Fopen.demonii.com%3A1337&amp;tr=udp%3A%2F%2Ftracker.coppersurfer.tk%3A6969&amp;tr=udp%3A%2F%2Fexodus.desync.com%3A6969","seeders":4,"leechers":3,"uploader":"EtHD","files":6,"time":1461837295,"description":"\n                EtHD - ExtraTorrent High-Definition\r\n\n                        \n                Survivor.S32E11.720p.WEB-DL.x264-FUM \r\n\n                        \n                [Format]:    Matroska\n[Duration]:    42mn 58s\n[Resolution]:  958 x 720 pixels\n[Display aspect ratio]:    16:9\n[Frame rate mode]:    Constant\n[Frame rate]:    29.970 fps\n\r\n\n                #EtHD -&gt; To avoid fakes, ALWAYS check that the torrent was added by EtHD\r\n\n                http://extratorrent.cc/\r\n\n                        \n                Help us by donating with Bitcoin: 1XeH1kKXWYbzZcFHokGiZ4d3MWW5WyXzU\r\n\nScreens...\r \nhttp://extraimago.com/image/amVm\r \nhttp://extraimago.com/image/amVi\r \nhttp://extraimago.com/image/amVl\r \nhttp://extraimago.com/image/amVI","torrent":{"xt":"urn:btih:1f67c90dc4b6d58402cdc7fa5cb38f93e73cb08b","amp;dn":"Survivor.S32E11.720p.WEB-DL.x264-FUM%5Bettv%5D","amp;tr":["udp%3A%2F%2Ftracker.leechers-paradise.org%3A6969","udp%3A%2F%2Fzer0day.ch%3A1337","udp%3A%2F%2Fopen.demonii.com%3A1337","udp%3A%2F%2Ftracker.coppersurfer.tk%3A6969","udp%3A%2F%2Fexodus.desync.com%3A6969"],"infoHash":"1f67c90dc4b6d58402cdc7fa5cb38f93e73cb08b","infoHashBuffer":{"type":"Buffer","data":[31,103,201,13,196,182,213,132,2,205,199,250,92,179,143,147,231,60,176,139]},"announce":[],"urlList":[]}}