{"title":"Missy Elliott - Discografia - Hip-Hop - 1997-2006 - (Inc covers)","uid":4746644,"size":633587502,"categoryP":"audio","categoryS":"music","magnet":"?xt=urn:btih:3b709c1c5f5a7df7be5cca8f83cb732fe82d727c&amp;dn=Missy+Elliott+-+Discografia+-+Hip-Hop+-+1997-2006+-+%28Inc+covers%29&amp;tr=udp%3A%2F%2Ftracker.openbittorrent.com%3A80&amp;tr=udp%3A%2F%2Fopen.demonii.com%3A1337&amp;tr=udp%3A%2F%2Ftracker.coppersurfer.tk%3A6969&amp;tr=udp%3A%2F%2Fexodus.desync.com%3A6969","seeders":4,"leechers":0,"uploader":"biggod99","files":126,"time":1235919901,"description":"Missy Elliott - Discografia - Hip-Hop - 1997-2006 - (Inc covers)\n\n\nSupa Dupa Fly (1997)\nDa Real World \nSo Addictive \nUnder Construction (2002)\nThis Is Not A Test (2003)\nThe Cookbook (2005) \nRespect M.E (2006)\n","torrent":{"xt":"urn:btih:3b709c1c5f5a7df7be5cca8f83cb732fe82d727c","amp;dn":"Missy+Elliott+-+Discografia+-+Hip-Hop+-+1997-2006+-+%28Inc+covers%29","amp;tr":["udp%3A%2F%2Ftracker.openbittorrent.com%3A80","udp%3A%2F%2Fopen.demonii.com%3A1337","udp%3A%2F%2Ftracker.coppersurfer.tk%3A6969","udp%3A%2F%2Fexodus.desync.com%3A6969"],"infoHash":"3b709c1c5f5a7df7be5cca8f83cb732fe82d727c","infoHashBuffer":{"type":"Buffer","data":[59,112,156,28,95,90,125,247,190,92,202,143,131,203,115,47,232,45,114,124]},"announce":[],"urlList":[]}}