{"title":"Art Pepper - The Intimate Art Pepper (2000) [EAC-FLAC]","uid":10668101,"size":360212483,"categoryP":"audio","categoryS":"flac","magnet":"?xt=urn:btih:459a72854ff684915403cf2230c4bc9ad2ae8aa9&amp;dn=Art+Pepper+-+The+Intimate+Art+Pepper+%282000%29+%5BEAC-FLAC%5D&amp;tr=udp%3A%2F%2Ftracker.openbittorrent.com%3A80&amp;tr=udp%3A%2F%2Fopen.demonii.com%3A1337&amp;tr=udp%3A%2F%2Ftracker.coppersurfer.tk%3A6969&amp;tr=udp%3A%2F%2Fexodus.desync.com%3A6969","seeders":4,"leechers":1,"uploader":"qculfj","files":11,"time":1406835220,"description":"01. In A Mellow Tone [10:08]\n02. Yesterdays [07:04]\n03. You Go To My Head [05:58]\n04. Tin Tin Deo [11:16]\n05. Body And Soul [04:35]\n06. Landscape [07:29]\n07. Anthropology [06:37]\n08. Desafinado [08:09]","torrent":{"xt":"urn:btih:459a72854ff684915403cf2230c4bc9ad2ae8aa9","amp;dn":"Art+Pepper+-+The+Intimate+Art+Pepper+%282000%29+%5BEAC-FLAC%5D","amp;tr":["udp%3A%2F%2Ftracker.openbittorrent.com%3A80","udp%3A%2F%2Fopen.demonii.com%3A1337","udp%3A%2F%2Ftracker.coppersurfer.tk%3A6969","udp%3A%2F%2Fexodus.desync.com%3A6969"],"infoHash":"459a72854ff684915403cf2230c4bc9ad2ae8aa9","infoHashBuffer":{"type":"Buffer","data":[69,154,114,133,79,246,132,145,84,3,207,34,48,196,188,154,210,174,138,169]},"announce":[],"urlList":[]}}