{"title":"D4VE_003_(2014)_(digital)_(Son_of_Ultron-Empire).cbr","uid":9669490,"size":39843767,"categoryP":"other","categoryS":"comics","magnet":"?xt=urn:btih:4d39aa22ff7eeee5f3cef8e44e6df2054e69f483&amp;dn=D4VE_003_%282014%29_%28digital%29_%28Son_of_Ultron-Empire%29.cbr&amp;tr=udp%3A%2F%2Ftracker.openbittorrent.com%3A80&amp;tr=udp%3A%2F%2Fopen.demonii.com%3A1337&amp;tr=udp%3A%2F%2Ftracker.coppersurfer.tk%3A6969&amp;tr=udp%3A%2F%2Fexodus.desync.com%3A6969","seeders":4,"leechers":0,"uploader":"nemesis43","files":1,"time":1393430849,"description":"D4VE_003_(2014)_(digital) ","torrent":{"xt":"urn:btih:4d39aa22ff7eeee5f3cef8e44e6df2054e69f483","amp;dn":"D4VE_003_%282014%29_%28digital%29_%28Son_of_Ultron-Empire%29.cbr","amp;tr":["udp%3A%2F%2Ftracker.openbittorrent.com%3A80","udp%3A%2F%2Fopen.demonii.com%3A1337","udp%3A%2F%2Ftracker.coppersurfer.tk%3A6969","udp%3A%2F%2Fexodus.desync.com%3A6969"],"infoHash":"4d39aa22ff7eeee5f3cef8e44e6df2054e69f483","infoHashBuffer":{"type":"Buffer","data":[77,57,170,34,255,126,238,229,243,206,248,228,78,109,242,5,78,105,244,131]},"announce":[],"urlList":[]}}