{"title":"[TeenFidelity] Violet Starr - Only 19 (16.09.2016)","uid":15839391,"size":666317898,"categoryP":"porn","categoryS":"movie_clips","magnet":"?xt=urn:btih:510961de5b35334a3336f7c2f9bf647b63a08241&amp;dn=%5BTeenFidelity%5D+Violet+Starr+-+Only+19+%2816.09.2016%29&amp;tr=udp%3A%2F%2Ftracker.leechers-paradise.org%3A6969&amp;tr=udp%3A%2F%2Fzer0day.ch%3A1337&amp;tr=udp%3A%2F%2Fopen.demonii.com%3A1337&amp;tr=udp%3A%2F%2Ftracker.coppersurfer.tk%3A6969&amp;tr=udp%3A%2F%2Fexodus.desync.com%3A6969","seeders":4,"leechers":1,"uploader":"SudoSu","files":1,"time":1474013337,"description":"[TeenFidelity] Violet Starr - Only 19 (16.09.2016)\r\n\r\n-------------------------\r\n ... : Screenshots : ... \r\n-------------------------  \nhttp://imgarte.com/?v=729155 \nhttp://imgarte.com/?v=760038\r\n\r\n\r\nMore exclusive porn at:  https://thepiratebay.se/user/SudoSu/\r\n   \nhttp://youpornbook.com","torrent":{"xt":"urn:btih:510961de5b35334a3336f7c2f9bf647b63a08241","amp;dn":"%5BTeenFidelity%5D+Violet+Starr+-+Only+19+%2816.09.2016%29","amp;tr":["udp%3A%2F%2Ftracker.leechers-paradise.org%3A6969","udp%3A%2F%2Fzer0day.ch%3A1337","udp%3A%2F%2Fopen.demonii.com%3A1337","udp%3A%2F%2Ftracker.coppersurfer.tk%3A6969","udp%3A%2F%2Fexodus.desync.com%3A6969"],"infoHash":"510961de5b35334a3336f7c2f9bf647b63a08241","infoHashBuffer":{"type":"Buffer","data":[81,9,97,222,91,53,51,74,51,54,247,194,249,191,100,123,99,160,130,65]},"announce":[],"urlList":[]}}