{"title":"Blueprint Tycoon v1.0.9","uid":15442272,"size":132158808,"categoryP":"games","categoryS":"pc","magnet":"?xt=urn:btih:5ec386d0f1431e874b74db8b9ac60f336290b0ef&amp;dn=Blueprint+Tycoon+v1.0.9&amp;tr=udp%3A%2F%2Ftracker.leechers-paradise.org%3A6969&amp;tr=udp%3A%2F%2Fzer0day.ch%3A1337&amp;tr=udp%3A%2F%2Fopen.demonii.com%3A1337&amp;tr=udp%3A%2F%2Ftracker.coppersurfer.tk%3A6969&amp;tr=udp%3A%2F%2Fexodus.desync.com%3A6969","seeders":4,"leechers":0,"uploader":"dauphong","files":1,"time":1469833966,"description":"Create your own Blueprints for each Crafter/Harvester using multiple Workers with a multitude of Tools and try to create the most productive Blueprints.\r\n\r\nProfit margins are razor thin so you must focus on ensuring peak efficiency at every point of your supply chain, if something breaks you must be swift in managing your cash flow before your treasury runs out and you face the wrath of unpaid Workers!","torrent":{"xt":"urn:btih:5ec386d0f1431e874b74db8b9ac60f336290b0ef","amp;dn":"Blueprint+Tycoon+v1.0.9","amp;tr":["udp%3A%2F%2Ftracker.leechers-paradise.org%3A6969","udp%3A%2F%2Fzer0day.ch%3A1337","udp%3A%2F%2Fopen.demonii.com%3A1337","udp%3A%2F%2Ftracker.coppersurfer.tk%3A6969","udp%3A%2F%2Fexodus.desync.com%3A6969"],"infoHash":"5ec386d0f1431e874b74db8b9ac60f336290b0ef","infoHashBuffer":{"type":"Buffer","data":[94,195,134,208,241,67,30,135,75,116,219,139,154,198,15,51,98,144,176,239]},"announce":[],"urlList":[]}}