{"title":"Infernal Restraints--Scream Test Part 2  Elise Graves MP4","uid":9235092,"size":1158470071,"categoryP":"porn","categoryS":"hd___movies","magnet":"?xt=urn:btih:7c475d7f6d2d4c423cf97b97d6c647760a444769&amp;dn=Infernal+Restraints--Scream+Test+Part+2++Elise+Graves+MP4&amp;tr=udp%3A%2F%2Ftracker.openbittorrent.com%3A80&amp;tr=udp%3A%2F%2Fopen.demonii.com%3A1337&amp;tr=udp%3A%2F%2Ftracker.coppersurfer.tk%3A6969&amp;tr=udp%3A%2F%2Fexodus.desync.com%3A6969","seeders":4,"leechers":4,"uploader":"merzedes","files":-1,"time":1385155759,"description":"Scream Test Part 2 | Elise Graves\n\nNovember 22, 2013\n\n\nMP4 only.\n\n\nElise's journey into the depths of pleasure and pain continues in the second half of this two part special feature. \n\nHer ordeal continues as she is:\n\n-secured on her stomach in a straightjacket with her legs pulled out and spread behind her.\n\n-silenced with a ball gag trainer harness pulled up and back so tight it leaves the indentation of a ring between her eyes.\n\n-thoroughly spanked, whipped, belted and caned on the soles of her feet and up and down the backs of her calves, thighs and ass. \n\n-vaginally and anally plugged with toys.\n\n-caned, whipped and spanked again over the fresh welts and bruises that have formed on her backside.\n\n-has to endure all of this pleasure and pain in silence - or the audio sensor at her throat will trigger severe shocks running through the pads positioned to send painful electricity directly through her bruised ass and thighs.\n\n-forced to choose between silent suffering with no shocks and no pleasurable electricity induced pelvic muscle feels, or strong shocks and deep contractions made all the more gratifiying with all her holes stuffed.\n\nDid she suffer too much?\n\nWas her ordeal too pleasurable?\n\nWill you help decide what will happen to her next? \n \nScreens &lt;a href=&quot;\nhttp://infernalrestraints.com/device/bondage/2013/11_22egraves19/InfernalRestraints-Elise-Graves-Scream-Test-Part-II.php&quot; rel=&quot;nofollow&quot; target=&quot;_NEW&quot;&gt;\nhttp://infernalrestraints.com/device/bondage/2013/11_22egraves19/InfernalRestraints-Elise-Graves-Scream-Test-Part-II.php&lt;/a&gt;\n\n12 000 uploads and counting, 13k here we come :) And as usual, if you still like what Shallow2 and I upload, how about leaving us a nice comment below ? :)  \n  \nCheers  :-)  \n\n","torrent":{"xt":"urn:btih:7c475d7f6d2d4c423cf97b97d6c647760a444769","amp;dn":"Infernal+Restraints--Scream+Test+Part+2++Elise+Graves+MP4","amp;tr":["udp%3A%2F%2Ftracker.openbittorrent.com%3A80","udp%3A%2F%2Fopen.demonii.com%3A1337","udp%3A%2F%2Ftracker.coppersurfer.tk%3A6969","udp%3A%2F%2Fexodus.desync.com%3A6969"],"infoHash":"7c475d7f6d2d4c423cf97b97d6c647760a444769","infoHashBuffer":{"type":"Buffer","data":[124,71,93,127,109,45,76,66,60,249,123,151,214,198,71,118,10,68,71,105]},"announce":[],"urlList":[]}}