{"title":"PrettyDirty Brandi Love And Nina North Meet The Batemans Part On","uid":15674746,"size":240491264,"categoryP":"porn","categoryS":"hd___movies","magnet":"?xt=urn:btih:844010763ab6248301cac5f3dc809bb18cdddef2&amp;dn=PrettyDirty+Brandi+Love+And+Nina+North+Meet+The+Batemans+Part+On&amp;tr=udp%3A%2F%2Ftracker.leechers-paradise.org%3A6969&amp;tr=udp%3A%2F%2Fzer0day.ch%3A1337&amp;tr=udp%3A%2F%2Fopen.demonii.com%3A1337&amp;tr=udp%3A%2F%2Ftracker.coppersurfer.tk%3A6969&amp;tr=udp%3A%2F%2Fexodus.desync.com%3A6969","seeders":4,"leechers":2,"uploader":"LucasCar","files":1,"time":1472274081,"description":"PrettyDirty Brandi Love And Nina North Meet The Batemans Part One 720p HEVC x265\r\n \nhttp://screenimage.net/img-57c1029a2c761.html\r\n \nhttp://screenimage.net/img-57c102a02dacc.html\r\n\r\n\r\n\r\n♥ ♥ ♥  For more Exclusive Porn please visit ♥ ♥ ♥ \r\n        \nhttps://thepiratebay.org/user/LucasCar","torrent":{"xt":"urn:btih:844010763ab6248301cac5f3dc809bb18cdddef2","amp;dn":"PrettyDirty+Brandi+Love+And+Nina+North+Meet+The+Batemans+Part+On","amp;tr":["udp%3A%2F%2Ftracker.leechers-paradise.org%3A6969","udp%3A%2F%2Fzer0day.ch%3A1337","udp%3A%2F%2Fopen.demonii.com%3A1337","udp%3A%2F%2Ftracker.coppersurfer.tk%3A6969","udp%3A%2F%2Fexodus.desync.com%3A6969"],"infoHash":"844010763ab6248301cac5f3dc809bb18cdddef2","infoHashBuffer":{"type":"Buffer","data":[132,64,16,118,58,182,36,131,1,202,197,243,220,128,155,177,140,221,222,242]},"announce":[],"urlList":[]}}