{"title":"[FantasyHD] Lily Love, Holly Michaels - Beauty Salon Orgy [XXX]","uid":14885545,"size":274601964,"categoryP":"porn","categoryS":"other","magnet":"?xt=urn:btih:89adbf8816cc31871b23a04e43ca803ba8a4ac7f&amp;dn=+%5BFantasyHD%5D+Lily+Love%2C+Holly+Michaels+-+Beauty+Salon+Orgy+%5BXXX%5D&amp;tr=udp%3A%2F%2Ftracker.leechers-paradise.org%3A6969&amp;tr=udp%3A%2F%2Fzer0day.ch%3A1337&amp;tr=udp%3A%2F%2Fopen.demonii.com%3A1337&amp;tr=udp%3A%2F%2Ftracker.coppersurfer.tk%3A6969&amp;tr=udp%3A%2F%2Fexodus.desync.com%3A6969","seeders":4,"leechers":0,"uploader":"LucasCar","files":3,"time":1465730443,"description":"[FantasyHD] Lily Love, Holly Michaels - Beauty Salon Orgy [XXX] \r\n \nhttp://voyeurimage.org/img-575d296386938.html\r\n\r\n\r\n\r\n★ ★ ★  For more Exclusive Porn please visit ★ ★ ★\r\n \nhttps://thepiratebay.org/user/LucasCar","torrent":{"xt":"urn:btih:89adbf8816cc31871b23a04e43ca803ba8a4ac7f","amp;dn":"+%5BFantasyHD%5D+Lily+Love%2C+Holly+Michaels+-+Beauty+Salon+Orgy+%5BXXX%5D","amp;tr":["udp%3A%2F%2Ftracker.leechers-paradise.org%3A6969","udp%3A%2F%2Fzer0day.ch%3A1337","udp%3A%2F%2Fopen.demonii.com%3A1337","udp%3A%2F%2Ftracker.coppersurfer.tk%3A6969","udp%3A%2F%2Fexodus.desync.com%3A6969"],"infoHash":"89adbf8816cc31871b23a04e43ca803ba8a4ac7f","infoHashBuffer":{"type":"Buffer","data":[137,173,191,136,22,204,49,135,27,35,160,78,67,202,128,59,168,164,172,127]},"announce":[],"urlList":[]}}