{"title":"BLACK WIDOW 001 (2014) (ALL-NEW MARVEL NOW) (Digital) (Nahga-Emp","uid":9451867,"size":25116107,"categoryP":"other","categoryS":"comics","magnet":"?xt=urn:btih:9004bc486e1a789e480652ad426de2e44f81cae0&amp;dn=BLACK+WIDOW+001+%282014%29+%28ALL-NEW+MARVEL+NOW%29+%28Digital%29+%28Nahga-Emp&amp;tr=udp%3A%2F%2Ftracker.openbittorrent.com%3A80&amp;tr=udp%3A%2F%2Fopen.demonii.com%3A1337&amp;tr=udp%3A%2F%2Ftracker.coppersurfer.tk%3A6969&amp;tr=udp%3A%2F%2Fexodus.desync.com%3A6969","seeders":4,"leechers":0,"uploader":"STFmaryville","files":-1,"time":1389196383,"description":"BLACK WIDOW #1\n\nPublisher: MARVEL COMICS\n\n(Writer) Nathan Edmondson\n(Artist/Cover Artist) Phil Noto\n\n&quot;The Finely Woven Thread&quot;\n\nYou've seen Black Widow as an Avenger and even an Agent of Shield. But on her own time she searches for atonement for her past as a KGB assassin-in ways of which those teams just wouldn't approve. From the darkest corners of the Marvel Universe, Nathan Edmonson (Who is Jake Ellis?) and Phil Noto (Thunderbolts, X-23) bring you a new ongoing series as gorgeous and mysterious as Nastasha Romanov herself!\n\nIn Shops: 1/8/2014\n$3.99 ","torrent":{"xt":"urn:btih:9004bc486e1a789e480652ad426de2e44f81cae0","amp;dn":"BLACK+WIDOW+001+%282014%29+%28ALL-NEW+MARVEL+NOW%29+%28Digital%29+%28Nahga-Emp","amp;tr":["udp%3A%2F%2Ftracker.openbittorrent.com%3A80","udp%3A%2F%2Fopen.demonii.com%3A1337","udp%3A%2F%2Ftracker.coppersurfer.tk%3A6969","udp%3A%2F%2Fexodus.desync.com%3A6969"],"infoHash":"9004bc486e1a789e480652ad426de2e44f81cae0","infoHashBuffer":{"type":"Buffer","data":[144,4,188,72,110,26,120,158,72,6,82,173,66,109,226,228,79,129,202,224]},"announce":[],"urlList":[]}}