{"title":"Anger Management S02E74 HDTV x264-LOL[ettv]","uid":11006321,"size":193142881,"categoryP":"video","categoryS":"tv_shows","magnet":"?xt=urn:btih:9309c8ba51e4ee1f5de2780587e56e284dbaf428&amp;dn=Anger+Management+S02E74+HDTV+x264-LOL%5Bettv%5D&amp;tr=udp%3A%2F%2Ftracker.openbittorrent.com%3A80&amp;tr=udp%3A%2F%2Fopen.demonii.com%3A1337&amp;tr=udp%3A%2F%2Ftracker.coppersurfer.tk%3A6969&amp;tr=udp%3A%2F%2Fexodus.desync.com%3A6969","seeders":4,"leechers":0,"uploader":"ettv","files":2,"time":1410239712,"description":"x264\nEncode Information\nResolution: 720x404\nVideo: x264\nAudio: AAC 2ch\nFrame Rate: 23.976024 fps\n","torrent":{"xt":"urn:btih:9309c8ba51e4ee1f5de2780587e56e284dbaf428","amp;dn":"Anger+Management+S02E74+HDTV+x264-LOL%5Bettv%5D","amp;tr":["udp%3A%2F%2Ftracker.openbittorrent.com%3A80","udp%3A%2F%2Fopen.demonii.com%3A1337","udp%3A%2F%2Ftracker.coppersurfer.tk%3A6969","udp%3A%2F%2Fexodus.desync.com%3A6969"],"infoHash":"9309c8ba51e4ee1f5de2780587e56e284dbaf428","infoHashBuffer":{"type":"Buffer","data":[147,9,200,186,81,228,238,31,93,226,120,5,135,229,110,40,77,186,244,40]},"announce":[],"urlList":[]}}