{"title":"Teen Manipulations 2 (NEW 2014 Forbidden Fruits Films) [DVDRip]","uid":10764134,"size":2411116836,"categoryP":"porn","categoryS":"movies","magnet":"?xt=urn:btih:9e6330f98e9868650127f8261b2db26643ec46d4&amp;dn=Teen+Manipulations+2+%28NEW+2014+Forbidden+Fruits+Films%29+%5BDVDRip%5D&amp;tr=udp%3A%2F%2Ftracker.openbittorrent.com%3A80&amp;tr=udp%3A%2F%2Fopen.demonii.com%3A1337&amp;tr=udp%3A%2F%2Ftracker.coppersurfer.tk%3A6969&amp;tr=udp%3A%2F%2Fexodus.desync.com%3A6969","seeders":4,"leechers":10,"uploader":"chkm8te","files":1,"time":1408006381,"description":"Teen Manipulations 2 (NEW 2014 Forbidden Fruits Films) [DVDRip]\n\nHalle Von, Tali Dova, Rahyndee James, Sabrina Banks, Tony D., Tony DeSergio, Levi Cash\n\nGood girls with no options.\nYouthful innocence is destroyed when good girls are forced to make bad choices. Four tales of young women exploited to satisfy opportunistic carnal desires!\n\nScreens: &lt;a href=&quot;\nhttp://xxxhost.me/viewer.php?file=ehiy6066u69vuhygql59.jpg&quot; rel=&quot;nofollow&quot; target=&quot;_NEW&quot;&gt;\nhttp://xxxhost.me/viewer.php?file=ehiy6066u69vuhygql59.jpg&lt;/a&gt;\n &lt;a href=&quot;\nhttp://xxxhost.me/viewer.php?file=kqq6ddcz6va8hzimybs6.jpg&quot; rel=&quot;nofollow&quot; target=&quot;_NEW&quot;&gt;\nhttp://xxxhost.me/viewer.php?file=kqq6ddcz6va8hzimybs6.jpg&lt;/a&gt;","torrent":{"xt":"urn:btih:9e6330f98e9868650127f8261b2db26643ec46d4","amp;dn":"Teen+Manipulations+2+%28NEW+2014+Forbidden+Fruits+Films%29+%5BDVDRip%5D","amp;tr":["udp%3A%2F%2Ftracker.openbittorrent.com%3A80","udp%3A%2F%2Fopen.demonii.com%3A1337","udp%3A%2F%2Ftracker.coppersurfer.tk%3A6969","udp%3A%2F%2Fexodus.desync.com%3A6969"],"infoHash":"9e6330f98e9868650127f8261b2db26643ec46d4","infoHashBuffer":{"type":"Buffer","data":[158,99,48,249,142,152,104,101,1,39,248,38,27,45,178,102,67,236,70,212]},"announce":[],"urlList":[]}}