{"title":"Passionate.For.Pussy.XXX.720P.WEBRIP.MP4-GUSH","uid":15480642,"size":3280992296,"categoryP":"porn","categoryS":"hd___movies","magnet":"?xt=urn:btih:a193b4a885dd9207232d968431a7b18ba437df73&amp;dn=Passionate.For.Pussy.XXX.720P.WEBRIP.MP4-GUSH&amp;tr=udp%3A%2F%2Ftracker.leechers-paradise.org%3A6969&amp;tr=udp%3A%2F%2Fzer0day.ch%3A1337&amp;tr=udp%3A%2F%2Fopen.demonii.com%3A1337&amp;tr=udp%3A%2F%2Ftracker.coppersurfer.tk%3A6969&amp;tr=udp%3A%2F%2Fexodus.desync.com%3A6969","seeders":4,"leechers":3,"uploader":"Borusssia","files":4,"time":1470249777,"description":"Screens\r\n \nhttp://www.imagesnake.org/show/75692/1.jpg \r\n \nhttp://www.imagesnake.org/show/75693/front.jpg","torrent":{"xt":"urn:btih:a193b4a885dd9207232d968431a7b18ba437df73","amp;dn":"Passionate.For.Pussy.XXX.720P.WEBRIP.MP4-GUSH","amp;tr":["udp%3A%2F%2Ftracker.leechers-paradise.org%3A6969","udp%3A%2F%2Fzer0day.ch%3A1337","udp%3A%2F%2Fopen.demonii.com%3A1337","udp%3A%2F%2Ftracker.coppersurfer.tk%3A6969","udp%3A%2F%2Fexodus.desync.com%3A6969"],"infoHash":"a193b4a885dd9207232d968431a7b18ba437df73","infoHashBuffer":{"type":"Buffer","data":[161,147,180,168,133,221,146,7,35,45,150,132,49,167,177,139,164,55,223,115]},"announce":[],"urlList":[]}}