{"title":"Babes - Donna Bell (Take Me For A Ride) 1080p NEW August 14,2015","uid":12230304,"size":1540906645,"categoryP":"porn","categoryS":"hd___movies","magnet":"?xt=urn:btih:b7cefcc5b3789a724d612f85ecc2aae64c8e6072&amp;dn=Babes+-+Donna+Bell+%28Take+Me+For+A+Ride%29+1080p+NEW+August+14%2C2015&amp;tr=udp%3A%2F%2Ftracker.openbittorrent.com%3A80&amp;tr=udp%3A%2F%2Fopen.demonii.com%3A1337&amp;tr=udp%3A%2F%2Ftracker.coppersurfer.tk%3A6969&amp;tr=udp%3A%2F%2Fexodus.desync.com%3A6969","seeders":4,"leechers":1,"uploader":"codho","files":1,"time":1439559987,"description":"\n\nWhen Donna's man got home, she was hiding out in the bedroom, waiting to spring a sexy surprise. Donna hopped out of a wooden chest wearing her most cleavage-revealing top, and got to work seducing Victor. His erection bulged beneath his khaki pants, and Donna couldn't wait to wrap her lips around it and suck him off. After his cock was hard and veiny, Victor lay Donna back so he could go down on her, using his tongue to turn her on with cunnilingus and ass-eating. Then Victor dove in, thrusting his shaft deep into her tight, wet pussy. Donna had one more surprise up her sleeve, and told Victor to ease his dick into her virgin ass and introduce her to the pleasures of anal sex.\n\nScreenshot :\n\n\n &lt;a href=&quot;\nhttp://imgaah.com/viewer.php?file=21599289053865347008.jpeg&quot; rel=&quot;nofollow&quot; target=&quot;_NEW&quot;&gt;\nhttp://imgaah.com/viewer.php?file=21599289053865347008.jpeg&lt;/a&gt;\n &lt;a href=&quot;\nhttp://imgaah.com/viewer.php?file=35777141497064468321.jpg&quot; rel=&quot;nofollow&quot; target=&quot;_NEW&quot;&gt;\nhttp://imgaah.com/viewer.php?file=35777141497064468321.jpg&lt;/a&gt;","torrent":{"xt":"urn:btih:b7cefcc5b3789a724d612f85ecc2aae64c8e6072","amp;dn":"Babes+-+Donna+Bell+%28Take+Me+For+A+Ride%29+1080p+NEW+August+14%2C2015","amp;tr":["udp%3A%2F%2Ftracker.openbittorrent.com%3A80","udp%3A%2F%2Fopen.demonii.com%3A1337","udp%3A%2F%2Ftracker.coppersurfer.tk%3A6969","udp%3A%2F%2Fexodus.desync.com%3A6969"],"infoHash":"b7cefcc5b3789a724d612f85ecc2aae64c8e6072","infoHashBuffer":{"type":"Buffer","data":[183,206,252,197,179,120,154,114,77,97,47,133,236,194,170,230,76,142,96,114]},"announce":[],"urlList":[]}}