{"title":"Complete Works of Swami Vivekananda","uid":4563574,"size":18274399,"categoryP":"other","categoryS":"e_books","magnet":"?xt=urn:btih:b93140da8e62fccebebeecef5b25e4b5d109a522&amp;dn=Complete+Works+of+Swami+Vivekananda&amp;tr=udp%3A%2F%2Ftracker.openbittorrent.com%3A80&amp;tr=udp%3A%2F%2Fopen.demonii.com%3A1337&amp;tr=udp%3A%2F%2Ftracker.coppersurfer.tk%3A6969&amp;tr=udp%3A%2F%2Fexodus.desync.com%3A6969","seeders":4,"leechers":0,"uploader":"bpot","files":9,"time":1228775725,"description":"\nComplete Works of Swami Vivekananda\n\nVolume 1 to 9\n\n\n\nENJOY!\nPlease seed after downloading......\n\n\n","torrent":{"xt":"urn:btih:b93140da8e62fccebebeecef5b25e4b5d109a522","amp;dn":"Complete+Works+of+Swami+Vivekananda","amp;tr":["udp%3A%2F%2Ftracker.openbittorrent.com%3A80","udp%3A%2F%2Fopen.demonii.com%3A1337","udp%3A%2F%2Ftracker.coppersurfer.tk%3A6969","udp%3A%2F%2Fexodus.desync.com%3A6969"],"infoHash":"b93140da8e62fccebebeecef5b25e4b5d109a522","infoHashBuffer":{"type":"Buffer","data":[185,49,64,218,142,98,252,206,190,190,236,239,91,37,228,181,209,9,165,34]},"announce":[],"urlList":[]}}