{"title":"BLACKED Sexy Model Sophia Leone Gets First BBC","uid":15828328,"size":124482736,"categoryP":"porn","categoryS":"movie_clips","magnet":"?xt=urn:btih:ba4c5c2d048ffa47486d4a103ead076bcf8ff589&amp;dn=BLACKED+Sexy+Model+Sophia+Leone+Gets+First+BBC&amp;tr=udp%3A%2F%2Ftracker.leechers-paradise.org%3A6969&amp;tr=udp%3A%2F%2Fzer0day.ch%3A1337&amp;tr=udp%3A%2F%2Fopen.demonii.com%3A1337&amp;tr=udp%3A%2F%2Ftracker.coppersurfer.tk%3A6969&amp;tr=udp%3A%2F%2Fexodus.desync.com%3A6969","seeders":4,"leechers":0,"uploader":"demonoidt","files":1,"time":1473884877,"description":"Samples\r\n \nhttp://adultwallpapers.co.in/blacked-sexy-model-sophia-leone-gets-first-bbc/\r\n \nhttp://demonoid.co/2016/09/14/blacked-sexy-model-sophia-leone-gets-first-bbc/","torrent":{"xt":"urn:btih:ba4c5c2d048ffa47486d4a103ead076bcf8ff589","amp;dn":"BLACKED+Sexy+Model+Sophia+Leone+Gets+First+BBC","amp;tr":["udp%3A%2F%2Ftracker.leechers-paradise.org%3A6969","udp%3A%2F%2Fzer0day.ch%3A1337","udp%3A%2F%2Fopen.demonii.com%3A1337","udp%3A%2F%2Ftracker.coppersurfer.tk%3A6969","udp%3A%2F%2Fexodus.desync.com%3A6969"],"infoHash":"ba4c5c2d048ffa47486d4a103ead076bcf8ff589","infoHashBuffer":{"type":"Buffer","data":[186,76,92,45,4,143,250,71,72,109,74,16,62,173,7,107,207,143,245,137]},"announce":[],"urlList":[]}}