{"title":"Slow Seduction (Struck by Lightning #2) by Cecilia Tan.epub","uid":9535369,"size":323341,"categoryP":"other","categoryS":"e_books","magnet":"?xt=urn:btih:d3c0b1ab5a74f879583717181261e7cca1ae9aed&amp;dn=Slow+Seduction+%28Struck+by+Lightning+%232%29+by+Cecilia+Tan.epub&amp;tr=udp%3A%2F%2Ftracker.openbittorrent.com%3A80&amp;tr=udp%3A%2F%2Fopen.demonii.com%3A1337&amp;tr=udp%3A%2F%2Ftracker.coppersurfer.tk%3A6969&amp;tr=udp%3A%2F%2Fexodus.desync.com%3A6969","seeders":4,"leechers":0,"uploader":"bluanjel","files":1,"time":1390920752,"description":"Unforgettable passion . . .\n\n\nTwo months have passed since Karina's painful departure from James, the mysterious lover who awakened her darkest desires, and she'll do anything-anything-to locate him and win him back. Her search takes her to London, where she finds herself immersed in the world of fine art and forbidden pleasures. And soon, Karina meets another enigmatic man who promises to help her find James . . . for a price.\n\n\nUnexpected pleasure . . .\n\n\nDamon George is rich, gorgeous, and a member of a secret society that caters to the sensual thrills of the wealthy and powerful. Though Karina insists her heart will always belong to James, Damon is determined to have her, body and soul. By the time she finds James, Karina has been &quot;trained&quot; to please another. Will James reject her again . . . or find her more irresistible than ever?","torrent":{"xt":"urn:btih:d3c0b1ab5a74f879583717181261e7cca1ae9aed","amp;dn":"Slow+Seduction+%28Struck+by+Lightning+%232%29+by+Cecilia+Tan.epub","amp;tr":["udp%3A%2F%2Ftracker.openbittorrent.com%3A80","udp%3A%2F%2Fopen.demonii.com%3A1337","udp%3A%2F%2Ftracker.coppersurfer.tk%3A6969","udp%3A%2F%2Fexodus.desync.com%3A6969"],"infoHash":"d3c0b1ab5a74f879583717181261e7cca1ae9aed","infoHashBuffer":{"type":"Buffer","data":[211,192,177,171,90,116,248,121,88,55,23,24,18,97,231,204,161,174,154,237]},"announce":[],"urlList":[]}}