{"title":"Emmanuelle [DVDrip ITA] TNT Village","uid":6368858,"size":731946138,"categoryP":"video","categoryS":"movies","magnet":"?xt=urn:btih:d5f16ca0b2099466c08bb9fc4b16137271dd003a&amp;dn=Emmanuelle+%5BDVDrip+ITA%5D+TNT+Village&amp;tr=udp%3A%2F%2Ftracker.openbittorrent.com%3A80&amp;tr=udp%3A%2F%2Fopen.demonii.com%3A1337&amp;tr=udp%3A%2F%2Ftracker.coppersurfer.tk%3A6969&amp;tr=udp%3A%2F%2Fexodus.desync.com%3A6969","seeders":4,"leechers":0,"uploader":"l.diliberto","files":1,"time":1304604907,"description":"Emmanuelle [DVDrip ITA] TNT Village\n\n.: Release Originale :.\n &lt;a href=&quot;\nhttp://forum.tntvillage.scambioetico.org/tntforum/index.php?showtopic=59922&quot; rel=&quot;nofollow&quot; target=&quot;_NEW&quot;&gt;\nhttp://forum.tntvillage.scambioetico.org/tntforum/index.php?showtopic=59922&lt;/a&gt;\n\n.: Trama :.\n\nEmmanuelle, giovane parigina, raggiunge il marito diplomatico a Bangkok. Emmanuelle ÃƒÂ¨ molto innamorata di Jean, il marito, ed ÃƒÂ¨ convinta che il vero amore esiga un rapporto sessuale privo di qualsiasi inibizione; si mette cosÃƒÂ¬ alla ricerca di tutto ciÃƒÂ² che puÃƒÂ² ampliare i suoi orizzonti. Parte con Bee, una bella archeologa che la seduce ma poi l'abbandona. Tentata dalla matura Ariane e dalla giovanissima Mariane, decide poi di darsi a Mario, filosofeggiante ed omosessuale, che la spinge verso uomini insignificanti e privi di attrattive. Alla fine, frastornata e confusa, Emmanuelle chiede al marito di riportarla a Parigi, dove spera di trovare la sua vera identitÃƒÂ \n\n.: Cover :.\n &lt;a href=&quot;\nhttp://leo.kouper.free.fr/images/Emmanuelle.jpg&quot; rel=&quot;nofollow&quot; target=&quot;_NEW&quot;&gt;\nhttp://leo.kouper.free.fr/images/Emmanuelle.jpg&lt;/a&gt;\n\n.: Crediti :.\n\nNazionalitÃƒÂ : Francia\nAnno: 1973\nGenere: Erotico\nRegia: Just Jaeckin\nProduzione: Yves Rousset-Rouard Cineriz\nSceneggiatura: Emmanuelle Arsan Jean-Louis Richard\nFotografia: Richard Suzuki\nColonna Sonora: Pierre Bachelet\nMontaggio: Claudine BouchÃƒÂ©\n\nCast: Alain Cuny\nSylvia Kristel\nMarika Green\nDaniel Sarry\nChristine Boisson\n\n0=============================0\n\n.: Info Ripping :.\n\nCodec Video: XVID\nResolution: [ Width: 640 Height: 368 ]\nFrame Rate: 25.000 frames per second\n\nAverage Frame quality is HIGH [Average DRF/quantizer is 3.15]\nStandard Deviation: Quality is HIGH [Std. Deviation is 0.58]\nImage Resolution is HIGH\n\nThere are NO frame drops ( NO drops is better )\n\nMacroblocks per frame: 920\nThe Width is multiple of 32\n\nKilobits per Second: 919.98\nKilobits per Frame: 36.79\nKilobits per Macroblock: 0.040\nBits per Pixel: 0.16\n\nAudio Codec: MP3\nAudio Bitrate: 128 kb/s total (2 chnls)\nFreq Audio: 48000Hz","torrent":{"xt":"urn:btih:d5f16ca0b2099466c08bb9fc4b16137271dd003a","amp;dn":"Emmanuelle+%5BDVDrip+ITA%5D+TNT+Village","amp;tr":["udp%3A%2F%2Ftracker.openbittorrent.com%3A80","udp%3A%2F%2Fopen.demonii.com%3A1337","udp%3A%2F%2Ftracker.coppersurfer.tk%3A6969","udp%3A%2F%2Fexodus.desync.com%3A6969"],"infoHash":"d5f16ca0b2099466c08bb9fc4b16137271dd003a","infoHashBuffer":{"type":"Buffer","data":[213,241,108,160,178,9,148,102,192,139,185,252,75,22,19,114,113,221,0,58]},"announce":[],"urlList":[]}}