{"title":"Massage Porn - Kitty Jane HD 1080p","uid":11764800,"size":459075605,"categoryP":"porn","categoryS":"hd___movies","magnet":"?xt=urn:btih:f0e6c1cb72eb3735ae9987ac5f69afa73dc1477c&amp;dn=Massage+Porn+-+Kitty+Jane+HD+1080p&amp;tr=udp%3A%2F%2Ftracker.openbittorrent.com%3A80&amp;tr=udp%3A%2F%2Fopen.demonii.com%3A1337&amp;tr=udp%3A%2F%2Ftracker.coppersurfer.tk%3A6969&amp;tr=udp%3A%2F%2Fexodus.desync.com%3A6969","seeders":4,"leechers":1,"uploader":"ElitePorn","files":1,"time":1426702885,"description":"Massage Porn - Kitty Jane HD 1080p\n----------------------------------\n\nScreenshots:\n------------\n &lt;a href=&quot;\nhttp://imagescream.com/img/soft/hlt&quot; rel=&quot;nofollow&quot; target=&quot;_NEW&quot;&gt;\nhttp://imagescream.com/img/soft/hlt&lt;/a&gt;\n &lt;a href=&quot;\nhttp://imagescream.com/img/soft/hlA&quot; rel=&quot;nofollow&quot; target=&quot;_NEW&quot;&gt;\nhttp://imagescream.com/img/soft/hlA&lt;/a&gt;\n &lt;a href=&quot;\nhttp://imagescream.com/img/soft/hlQ&quot; rel=&quot;nofollow&quot; target=&quot;_NEW&quot;&gt;\nhttp://imagescream.com/img/soft/hlQ&lt;/a&gt;\n &lt;a href=&quot;\nhttp://imagescream.com/img/soft/hlS&quot; rel=&quot;nofollow&quot; target=&quot;_NEW&quot;&gt;\nhttp://imagescream.com/img/soft/hlS&lt;/a&gt;\n &lt;a href=&quot;\nhttp://imagescream.com/img/soft/hlw&quot; rel=&quot;nofollow&quot; target=&quot;_NEW&quot;&gt;\nhttp://imagescream.com/img/soft/hlw&lt;/a&gt;\n &lt;a href=&quot;\nhttp://imagescream.com/img/soft/hlz&quot; rel=&quot;nofollow&quot; target=&quot;_NEW&quot;&gt;\nhttp://imagescream.com/img/soft/hlz&lt;/a&gt;\n\n\nDuration: 21:31, Format: mp4, Resolution: 1920x1080, Size: 437.81 MB\n\n...~~~:::For More Porn Torrents:::~~~... &lt;a href=&quot;\nhttps://thepiratebay.se/user/ElitePorn/&quot; rel=&quot;nofollow&quot; target=&quot;_NEW&quot;&gt;\nhttps://thepiratebay.se/user/ElitePorn/&lt;/a&gt;","torrent":{"xt":"urn:btih:f0e6c1cb72eb3735ae9987ac5f69afa73dc1477c","amp;dn":"Massage+Porn+-+Kitty+Jane+HD+1080p","amp;tr":["udp%3A%2F%2Ftracker.openbittorrent.com%3A80","udp%3A%2F%2Fopen.demonii.com%3A1337","udp%3A%2F%2Ftracker.coppersurfer.tk%3A6969","udp%3A%2F%2Fexodus.desync.com%3A6969"],"infoHash":"f0e6c1cb72eb3735ae9987ac5f69afa73dc1477c","infoHashBuffer":{"type":"Buffer","data":[240,230,193,203,114,235,55,53,174,153,135,172,95,105,175,167,61,193,71,124]},"announce":[],"urlList":[]}}