{"title":"Round And Brown Vol. 37 (NEW 2015 Reality Kings) [Split Scenes] ","uid":12130718,"size":2557388441,"categoryP":"porn","categoryS":"movies","magnet":"?xt=urn:btih:f7da9bc90befc7542d19f31933e49ab7088774d7&amp;dn=Round+And+Brown+Vol.+37+%28NEW+2015+Reality+Kings%29+%5BSplit+Scenes%5D+&amp;tr=udp%3A%2F%2Ftracker.openbittorrent.com%3A80&amp;tr=udp%3A%2F%2Fopen.demonii.com%3A1337&amp;tr=udp%3A%2F%2Ftracker.coppersurfer.tk%3A6969&amp;tr=udp%3A%2F%2Fexodus.desync.com%3A6969","seeders":4,"leechers":39,"uploader":"chkm8te","files":6,"time":1437034860,"description":"Round And Brown Vol. 37 (NEW 2015 Reality Kings) [Split Scenes] WEB-DL\n\nHarley Dean, Baby Cakes, Danielle Reid, Tamra Millan\n\nCovers: &lt;a href=&quot;\nhttp://xxxhost.me/viewer.php?file=sixdttgxhtddofan0twk.jpg&quot; rel=&quot;nofollow&quot; target=&quot;_NEW&quot;&gt;\nhttp://xxxhost.me/viewer.php?file=sixdttgxhtddofan0twk.jpg&lt;/a&gt;\n\nScreens: &lt;a href=&quot;\nhttp://xxxhost.me/viewer.php?file=np4lthf9xu96mznk2tpo.jpg&quot; rel=&quot;nofollow&quot; target=&quot;_NEW&quot;&gt;\nhttp://xxxhost.me/viewer.php?file=np4lthf9xu96mznk2tpo.jpg&lt;/a&gt;\n &lt;a href=&quot;\nhttp://xxxhost.me/viewer.php?file=im8r03iitl1uiuz5l94b.jpg&quot; rel=&quot;nofollow&quot; target=&quot;_NEW&quot;&gt;\nhttp://xxxhost.me/viewer.php?file=im8r03iitl1uiuz5l94b.jpg&lt;/a&gt;\n &lt;a href=&quot;\nhttp://xxxhost.me/viewer.php?file=4jkjx8b24vthnhrv0q8i.jpg&quot; rel=&quot;nofollow&quot; target=&quot;_NEW&quot;&gt;\nhttp://xxxhost.me/viewer.php?file=4jkjx8b24vthnhrv0q8i.jpg&lt;/a&gt;\n &lt;a href=&quot;\nhttp://xxxhost.me/viewer.php?file=aw3mwxmmwmopjin4zp5c.jpg&quot; rel=&quot;nofollow&quot; target=&quot;_NEW&quot;&gt;\nhttp://xxxhost.me/viewer.php?file=aw3mwxmmwmopjin4zp5c.jpg&lt;/a&gt;\n &lt;a href=&quot;\nhttp://xxxhost.me/viewer.php?file=jhn6cpl2r5niqbf9gp1o.jpg&quot; rel=&quot;nofollow&quot; target=&quot;_NEW&quot;&gt;\nhttp://xxxhost.me/viewer.php?file=jhn6cpl2r5niqbf9gp1o.jpg&lt;/a&gt;\n &lt;a href=&quot;\nhttp://xxxhost.me/viewer.php?file=jenc25d1aidrwejkib09.jpg&quot; rel=&quot;nofollow&quot; target=&quot;_NEW&quot;&gt;\nhttp://xxxhost.me/viewer.php?file=jenc25d1aidrwejkib09.jpg&lt;/a&gt;","torrent":{"xt":"urn:btih:f7da9bc90befc7542d19f31933e49ab7088774d7","amp;dn":"Round+And+Brown+Vol.+37+%28NEW+2015+Reality+Kings%29+%5BSplit+Scenes%5D+","amp;tr":["udp%3A%2F%2Ftracker.openbittorrent.com%3A80","udp%3A%2F%2Fopen.demonii.com%3A1337","udp%3A%2F%2Ftracker.coppersurfer.tk%3A6969","udp%3A%2F%2Fexodus.desync.com%3A6969"],"infoHash":"f7da9bc90befc7542d19f31933e49ab7088774d7","infoHashBuffer":{"type":"Buffer","data":[247,218,155,201,11,239,199,84,45,25,243,25,51,228,154,183,8,135,116,215]},"announce":[],"urlList":[]}}